toci/Toci.py
toci/__init__.py
toci-0.0.3.dist-info/LICENSE
toci-0.0.3.dist-info/METADATA
toci-0.0.3.dist-info/WHEEL
toci-0.0.3.dist-info/entry_points.txt
toci-0.0.3.dist-info/top_level.txt
toci-0.0.3.dist-info/RECORD
