Metadata-Version: 2.1
Name: toci
Version: 0.0.3
Summary: markdown tool to create table of content from jupyter notebooks
Home-page: https://github.com/ozlerhakan/toci
Author: Hakan Ozler
Author-email: ozler.hakan@gmail.com
License: MIT
Project-URL: Bug Tracker, https://github.com/ozlerhakan/toci/issues
Keywords: python,jupyter,notebook,markdown,toc
Platform: linux
Platform: unix
Classifier: Programming Language :: Python :: 3
Classifier: License :: OSI Approved :: MIT License
Classifier: Operating System :: OS Independent
Requires-Python: >=3.7
License-File: LICENSE
Requires-Dist: nbconvert (>=6.2.0)
Requires-Dist: nbformat (>=5.1.3)
Requires-Dist: mistune (==0.8.4)
